bizkaibus/__init__.py
bizkaibus/bizkaibusAPI.py
bizkaibus/const.py
bizkaibus/Model/BizkaibusArrival.py
bizkaibus/Model/BizkaibusArrivalTime.py
bizkaibus/Model/BizkaibusLanguages.py
bizkaibus/Model/BizkaibusLine.py
bizkaibus/Model/BizkaibusTimetable.py
bizkaibus/Model/__init__.py
bizkaibus/ServiceParams/BizkaibusServiceParam.py
bizkaibus/ServiceParams/LineItineraryServiceParam.py
bizkaibus/ServiceParams/LinesInTownServiceParam.py
bizkaibus/ServiceParams/StopInfoServiceParam.py
bizkaibus/ServiceParams/TimetableServiceParam.py
bizkaibus/ServiceParams/__init__.py
bizkaibus-0.5.2.dist-info/licenses/LICENSE
bizkaibus-0.5.2.dist-info/licenses/LICENSE.txt
bizkaibus-0.5.2.dist-info/METADATA
bizkaibus-0.5.2.dist-info/WHEEL
bizkaibus-0.5.2.dist-info/top_level.txt
bizkaibus-0.5.2.dist-info/RECORD
