Metadata-Version: 2.4
Name: bizkaibus
Version: 0.5.2
Summary: Online information for buses of Biscay bus services (Basque Country, Spain).
Author-email: Ugaitz Etxebarria <etxeba17@gmail.com>
License-Expression: MIT
Project-URL: Homepage, https://github.com/UgaitzEtxebarria/BizkaibusRTPI
Project-URL: Download, https://github.com/UgaitzEtxebarria/BizkaibusRTPI/archive/0.3.0.tar.gz
Keywords: Bizkaibus,Bizkaia,Autobusa,rtpi,buses
Classifier: Development Status :: 3 - Alpha
Classifier: Intended Audience :: Developers
Classifier: Topic :: Software Development :: Build Tools
Classifier: Programming Language :: Python :: 3
Classifier: Programming Language :: Python :: 3.6
Classifier: Programming Language :: Python :: 3.7
Classifier: Programming Language :: Python :: 3.8
Classifier: Programming Language :: Python :: 3.9
Requires-Python: >=3.6
License-File: LICENSE
License-File: LICENSE.txt
Requires-Dist: aiohttp
Dynamic: license-file
